ntnx_dataprotection_py_client/__init__.py
ntnx_dataprotection_py_client/api_client.py
ntnx_dataprotection_py_client/api_response.py
ntnx_dataprotection_py_client/configuration.py
ntnx_dataprotection_py_client/custom_retry.py
ntnx_dataprotection_py_client/rest.py
ntnx_dataprotection_py_client/api/__init__.py
ntnx_dataprotection_py_client/api/consistency_groups_api.py
ntnx_dataprotection_py_client/api/data_protection_cluster_capabilities_api.py
ntnx_dataprotection_py_client/api/protected_resources_api.py
ntnx_dataprotection_py_client/api/recovery_plan_actions_api.py
ntnx_dataprotection_py_client/api/recovery_plan_jobs_api.py
ntnx_dataprotection_py_client/api/recovery_points_api.py
ntnx_dataprotection_py_client/models/__init__.py
ntnx_dataprotection_py_client/models/OneOfcommon/__init__.py
ntnx_dataprotection_py_client/models/OneOfcommon/v1/__init__.py
ntnx_dataprotection_py_client/models/OneOfcommon/v1/config/KVPairvalue.py
ntnx_dataprotection_py_client/models/OneOfcommon/v1/config/__init__.py
ntnx_dataprotection_py_client/models/OneOfdataprotection/__init__.py
ntnx_dataprotection_py_client/models/OneOfdataprotection/v4/__init__.py
ntnx_dataprotection_py_client/models/OneOfdataprotection/v4/common/BaseVmRecoveryPointapplication_consistent_properties.py
ntnx_dataprotection_py_client/models/OneOfdataprotection/v4/common/__init__.py
ntnx_dataprotection_py_client/models/OneOfdataprotection/v4/config/ClusterInfoApiResponsedata.py
ntnx_dataprotection_py_client/models/OneOfdataprotection/v4/config/CreateConsistencyGroupApiResponsedata.py
ntnx_dataprotection_py_client/models/OneOfdataprotection/v4/config/CreateRecoveryPointApiResponsedata.py
ntnx_dataprotection_py_client/models/OneOfdataprotection/v4/config/DeleteConsistencyGroupApiResponsedata.py
ntnx_dataprotection_py_client/models/OneOfdataprotection/v4/config/DeleteRecoveryPlanJobApiResponsedata.py
ntnx_dataprotection_py_client/models/OneOfdataprotection/v4/config/DeleteRecoveryPointApiResponsedata.py
ntnx_dataprotection_py_client-4.2.1.dist-info/LICENSE.txt
ntnx_dataprotection_py_client-4.2.1.dist-info/METADATA
ntnx_dataprotection_py_client-4.2.1.dist-info/WHEEL
ntnx_dataprotection_py_client-4.2.1.dist-info/top_level.txt
ntnx_dataprotection_py_client-4.2.1.dist-info/RECORD
